history.py
reading.py
title.py
word_list.py
word_test.py
libs/apikey.py
libs/common.py
libs/newdate.py
nanpapp2-1.0.1.dist-info/LICENSE
nanpapp2-1.0.1.dist-info/METADATA
nanpapp2-1.0.1.dist-info/WHEEL
nanpapp2-1.0.1.dist-info/entry_points.txt
nanpapp2-1.0.1.dist-info/top_level.txt
nanpapp2-1.0.1.dist-info/RECORD
