Metadata-Version: 2.1
Name: nanpapp2
Version: 1.0.1
Summary: English Learning Application
Author-email: nanp1311 <pengin.na11@gmail.com>
Project-URL: Homepage, https://github.com/nanp1311/untitled
Project-URL: Bug Tracker, https://github.com/nanp1311/untitled/issues
Classifier: Programming Language :: Python :: 3
Classifier: License :: OSI Approved :: MIT License
Classifier: Operating System :: OS Independent
Requires-Python: >=3.8
License-File: LICENSE
Requires-Dist: openai ~=0.28
Requires-Dist: wxPython ~=4.2.1
Requires-Dist: plotly ~=5.16.1
